colcon/__init__.py
colcon/__main__.py
colcon_core/__init__.py
colcon_core/argument_default.py
colcon_core/argument_type.py
colcon_core/command.py
colcon_core/dependency_descriptor.py
colcon_core/entry_point.py
colcon_core/environment_variable.py
colcon_core/event_reactor.py
colcon_core/extension_point.py
colcon_core/feature_flags.py
colcon_core/generic_decorator.py
colcon_core/location.py
colcon_core/logging.py
colcon_core/package_decorator.py
colcon_core/package_descriptor.py
colcon_core/plugin_system.py
colcon_core/python_install_path.py
colcon_core/subprocess.py
colcon_core/topological_order.py
colcon_core/argument_parser/__init__.py
colcon_core/argument_parser/action_collector.py
colcon_core/argument_parser/destination_collector.py
colcon_core/argument_parser/type_collector.py
colcon_core/distutils/__init__.py
colcon_core/distutils/commands/__init__.py
colcon_core/distutils/commands/symlink_data.py
colcon_core/environment/__init__.py
colcon_core/environment/path.py
colcon_core/environment/pythonpath.py
colcon_core/event/__init__.py
colcon_core/event/command.py
colcon_core/event/job.py
colcon_core/event/output.py
colcon_core/event/test.py
colcon_core/event/timer.py
colcon_core/event_handler/__init__.py
colcon_core/event_handler/console_direct.py
colcon_core/event_handler/console_start_end.py
colcon_core/event_handler/log_command.py
colcon_core/executor/__init__.py
colcon_core/executor/sequential.py
colcon_core/output_style/__init__.py
colcon_core/output_style/__main__.py
colcon_core/package_augmentation/__init__.py
colcon_core/package_augmentation/python.py
colcon_core/package_discovery/__init__.py
colcon_core/package_discovery/path.py
colcon_core/package_identification/__init__.py
colcon_core/package_identification/ignore.py
colcon_core/package_identification/python.py
colcon_core/package_selection/__init__.py
colcon_core/prefix_path/__init__.py
colcon_core/prefix_path/colcon.py
colcon_core/pytest/__init__.py
colcon_core/pytest/hooks.py
colcon_core-0.20.1.dist-info/LICENSE
colcon_core-0.20.1.dist-info/METADATA
colcon_core-0.20.1.dist-info/WHEEL
colcon_core-0.20.1.dist-info/entry_points.txt
colcon_core-0.20.1.dist-info/top_level.txt
colcon_core/task/python/colcon_distutils_commands/colcon_distutils_commands-0.0.0.dist-info/METADATA
colcon_core/task/python/colcon_distutils_commands/colcon_distutils_commands-0.0.0.dist-info/entry_points.txt
colcon_core-0.20.1.dist-info/RECORD
